django_tasix-0.3.0.dist-info/DESCRIPTION.rst
django_tasix-0.3.0.dist-info/METADATA
django_tasix-0.3.0.dist-info/RECORD
django_tasix-0.3.0.dist-info/WHEEL
django_tasix-0.3.0.dist-info/metadata.json
django_tasix-0.3.0.dist-info/top_level.txt
tasix/__init__.py
tasix/apps.py
tasix/decorators.py
tasix/middleware.py
tasix/models.py
tasix/network.py
tasix/tests.py
