Metadata-Version: 2.0
Name: django-tasix
Version: 0.3.0
Summary: Simple django app to allow/block IP addresses and ranges outside the Tas-IX network
Home-page: https://github.com/muminoff/django-tasix
Author: Sardor Muminov
Author-email: smuminov@gmail.com
License: BSD
Platform: UNKNOWN
Classifier: Development Status :: 4 - Beta
Classifier: Environment :: Web Environment
Classifier: Framework :: Django
Classifier: Intended Audience :: Developers
Classifier: License :: OSI Approved :: BSD License
Classifier: Operating System :: OS Independent
Classifier: Programming Language :: Python
Classifier: Topic :: Internet :: WWW/HTTP
Requires-Dist: netaddr
